design.sv
module receiver (
    input clk,
    input rst,
    input rx,              // Serial bitstream input
    output reg [3:0] data, // Received 4-bit data
    output reg done        // Done pulse when valid byte received
);

    // State encoding using parameters (Verilog style)
    parameter IDLE      = 3'd0,
              RECEIVE   = 3'd1,
              WAIT_STOP = 3'd2,
              DONE      = 3'd3,
              ERROR     = 3'd4;

    reg [2:0] state, next_state;

    reg [2:0] bit_cnt;
    reg [3:0] shift_reg;

    // Sequential logic
    always @(posedge clk or posedge rst) begin
        if (rst) begin
            state      <= IDLE;
            bit_cnt    <= 3'd0;
            shift_reg  <= 4'd0;
            data       <= 4'd0;
            done       <= 1'b0;
        end else begin
            state <= next_state;

            case (state)
                IDLE: begin
                    done <= 1'b0;
                    if (rx == 1'b0) begin  // Start bit detected
                        bit_cnt   <= 3'd0;
                        shift_reg <= 4'd0;
                    end
                end

                RECEIVE: begin
                    shift_reg <= {rx, shift_reg[3:1]};
                    bit_cnt   <= bit_cnt + 1;
                end

                WAIT_STOP: begin
                    if (rx == 1'b1) begin
                        data <= shift_reg;
                        done <= 1'b1;
                    end
                end

                DONE: begin
                    done <= 1'b0;
                end

                ERROR: begin
                    done <= 1'b0;
                end
            endcase
        end
    end

    // Combinational next-state logic
    always @(*) begin
        next_state = state;
        case (state)
            IDLE:
                next_state = (rx == 1'b0) ? RECEIVE : IDLE;

            RECEIVE:
                next_state = (bit_cnt == 3'd3) ? WAIT_STOP : RECEIVE;

            WAIT_STOP:
                next_state = (rx == 1'b1) ? DONE : ERROR;

            DONE:
                next_state = IDLE;

            ERROR:
                next_state = (rx == 1'b1) ? IDLE : ERROR;
        endcase
    end

endmodule

testbench.sv
`timescale 1ns / 1ps

module tb_receiver;

    // Inputs
    reg clk;
    reg rst;
    reg rx;

    // Outputs
    wire [3:0] data;
    wire done;

    // Instantiate the receiver module (DUT)
    receiver uut (
        .clk(clk),
        .rst(rst),
        .rx(rx),
        .data(data),
        .done(done)
    );

    // Clock generation: 10ns period (100MHz)
    always #5 clk = ~clk;

    // Task to send a 6-bit framed packet: start, 4 data bits (LSB first), stop
    task send_packet(input [3:0] payload);
        integer i;
        begin
            @(posedge clk); #1 rx <= 0; // Start bit
            @(posedge clk); #1;

            for (i = 0; i < 4; i = i + 1) begin
                rx <= payload[i];       // LSB first
                @(posedge clk); #1;
            end

            rx <= 1; // Stop bit
            @(posedge clk); #1;
        end
    endtask

    // Simulation sequence
    initial begin
        // Initialize signals
        clk = 0;
        rst = 1;
        rx  = 1;

        // Hold reset for 2 cycles
        repeat (2) @(posedge clk);
        rst = 0;

        // Send valid packet: 4'b1010
        send_packet(4'b1010);
        repeat (4) @(posedge clk);

        // Send valid packet: 4'b0111
        send_packet(4'b0111);
        repeat (4) @(posedge clk);

        // Send invalid packet: correct start, incorrect stop
        @(posedge clk); #1 rx <= 0;  // Start bit
        @(posedge clk); #1 rx <= 1;
        @(posedge clk); #1 rx <= 0;
        @(posedge clk); #1 rx <= 1;
        @(posedge clk); #1 rx <= 1;
        @(posedge clk); #1 rx <= 0;  // Invalid stop bit

        // Idle recovery
        repeat (6) @(posedge clk); #1;
        rx <= 1;

        // Final valid packet: 4'b1100
        repeat (2) @(posedge clk);
        send_packet(4'b1100);

        // End simulation
        repeat (10) @(posedge clk);
        $finish;
    end

    // EPWave waveform generation
    initial begin
        $dumpfile("receiver.vcd");
        $dumpvars(1, tb_receiver);
        $dumpvars(1, uut);
    end

endmodule

receiver.vcd
$date
	Wed Jun 25 02:07:41 2025
$end
$version
	Icarus Verilog
$end
$timescale
	1ps
$end
$scope module tb_receiver $end
$var wire 1 ! done $end
$var wire 4 " data [3:0] $end
$var reg 1 # clk $end
$var reg 1 $ rst $end
$var reg 1 % rx $end
$upscope $end
$scope module tb_receiver $end
$scope module uut $end
$var wire 1 # clk $end
$var wire 1 $ rst $end
$var wire 1 % rx $end
$var parameter 3 & DONE $end
$var parameter 3 ' ERROR $end
$var parameter 3 ( IDLE $end
$var parameter 3 ) RECEIVE $end
$var parameter 3 * WAIT_STOP $end
$var reg 3 + bit_cnt [2:0] $end
$var reg 4 , data [3:0] $end
$var reg 1 ! done $end
$var reg 3 - next_state [2:0] $end
$var reg 4 . shift_reg [3:0] $end
$var reg 3 / state [2:0] $end
$upscope $end
$upscope $end
$enddefinitions $end
$comment Show the parameter values. $end
$dumpall
b10 *
b1 )
b0 (
b100 '
b11 &
$end
#0
$dumpvars
b0 /
b0 .
b0 -
b0 ,
b0 +
1%
1$
0#
b0 "
0!
$end
#5000
1#
#10000
0#
#15000
0$
1#
#20000
0#
#25000
1#
#26000
b1 -
0%
#30000
0#
#35000
b1 /
1#
#40000
0#
#45000
b1 +
1#
#46000
1%
#50000
0#
#55000
b10 +
b1000 .
1#
#56000
0%
#60000
0#
#65000
b10 -
b11 +
b100 .
1#
#66000
b10 -
1%
#70000
0#
#75000
b11 -
b100 +
b1010 .
b10 /
1#
#80000
0#
#85000
b0 -
1!
b1010 "
b1010 ,
b11 /
1#
#90000
0#
#95000
0!
b0 /
1#
#100000
0#
#105000
1#
#110000
0#
#115000
1#
#120000
0#
#125000
1#
#130000
0#
#135000
1#
#136000
b1 -
0%
#140000
0#
#145000
b0 .
b0 +
b1 /
1#
#146000
1%
#150000
0#
#155000
b1 +
b1000 .
1#
#160000
0#
#165000
b10 +
b1100 .
1#
#170000
0#
#175000
b10 -
b11 +
b1110 .
1#
#176000
b10 -
0%
#180000
0#
#185000
b100 -
b100 +
b111 .
b10 /
1#
#186000
b11 -
1%
#190000
0#
#195000
b0 -
1!
b111 "
b111 ,
b11 /
1#
#200000
0#
#205000
0!
b0 /
1#
#210000
0#
#215000
1#
#220000
0#
#225000
1#
#230000
0#
#235000
1#
#240000
0#
#245000
1#
#246000
b1 -
0%
#250000
0#
#255000
b0 .
b0 +
b1 /
1#
#256000
1%
#260000
0#
#265000
b1 +
b1000 .
1#
#266000
0%
#270000
0#
#275000
b10 +
b100 .
1#
#276000
1%
#280000
0#
#285000
b10 -
b11 +
b1010 .
1#
#290000
0#
#295000
b11 -
b100 +
b1101 .
b10 /
1#
#296000
b100 -
0%
#300000
0#
#305000
b100 /
1#
#310000
0#
#315000
1#
#320000
0#
#325000
1#
#330000
0#
#335000
1#
#340000
0#
#345000
1#
#350000
0#
#355000
1#
#356000
b0 -
1%
#360000
0#
#365000
b0 /
1#
#370000
0#
#375000
1#
#380000
0#
#385000
1#
#386000
b1 -
0%
#390000
0#
#395000
b0 .
b0 +
b1 /
1#
#400000
0#
#405000
b1 +
1#
#410000
0#
#415000
b10 +
1#
#416000
1%
#420000
0#
#425000
b10 -
b11 +
b1000 .
1#
#430000
0#
#435000
b11 -
b100 +
b1100 .
b10 /
1#
#440000
0#
#445000
b0 -
1!
b1100 "
b1100 ,
b11 /
1#
#450000
0#
#455000
0!
b0 /
1#
